[
    {
        "name": "Ryan Mountcastle",
        "player_id": 663624,
        "hits": 2,
        "singles": 2,
        "doubles": 0,
        "triples": 0,
        "home_runs": 0,
        "at_bats": 3,
        "team": "BAL",
        "headshot_url": "https://img.mlbstatic.com/mlb-photos/image/upload/w_213,d_people:generic:headshot:silo:current.png,q_auto:best,f_auto/v1/people/663624/headshot/67/current",
        "obp": 0.667,
        "season_obp": 0.28,
        "difference_obp": 0.387
    },
    {
        "name": "Otto Lopez",
        "player_id": 672640,
        "hits": 11,
        "singles": 8,
        "doubles": 2,
        "triples": 0,
        "home_runs": 1,
        "at_bats": 21,
        "team": "MIA",
        "headshot_url": "https://img.mlbstatic.com/mlb-photos/image/upload/w_213,d_people:generic:headshot:silo:current.png,q_auto:best,f_auto/v1/people/672640/headshot/67/current",
        "obp": 0.583,
        "season_obp": 0.327,
        "difference_obp": 0.256
    },
    {
        "name": "George Springer",
        "player_id": 543807,
        "hits": 11,
        "singles": 10,
        "doubles": 0,
        "triples": 0,
        "home_runs": 1,
        "at_bats": 19,
        "team": "TOR",
        "headshot_url": "https://img.mlbstatic.com/mlb-photos/image/upload/w_213,d_people:generic:headshot:silo:current.png,q_auto:best,f_auto/v1/people/543807/headshot/67/current",
        "obp": 0.6,
        "season_obp": 0.358,
        "difference_obp": 0.242
    },
    {
        "name": "Zach Neto",
        "player_id": 687263,
        "hits": 7,
        "singles": 3,
        "doubles": 2,
        "triples": 0,
        "home_runs": 2,
        "at_bats": 14,
        "team": "LAA",
        "headshot_url": "https://img.mlbstatic.com/mlb-photos/image/upload/w_213,d_people:generic:headshot:silo:current.png,q_auto:best,f_auto/v1/people/687263/headshot/67/current",
        "obp": 0.533,
        "season_obp": 0.321,
        "difference_obp": 0.212
    },
    {
        "name": "Cam Smith",
        "player_id": 701358,
        "hits": 7,
        "singles": 6,
        "doubles": 0,
        "triples": 0,
        "home_runs": 1,
        "at_bats": 16,
        "team": "HOU",
        "headshot_url": "https://img.mlbstatic.com/mlb-photos/image/upload/w_213,d_people:generic:headshot:silo:current.png,q_auto:best,f_auto/v1/people/701358/headshot/67/current",
        "obp": 0.55,
        "season_obp": 0.343,
        "difference_obp": 0.207
    }
]