[
    {
        "name": "Gavin Sheets",
        "player_id": 657757,
        "hits": 8,
        "singles": 5,
        "doubles": 2,
        "triples": 0,
        "home_runs": 1,
        "at_bats": 17,
        "team": "SDP",
        "headshot_url": "https://img.mlbstatic.com/mlb-photos/image/upload/w_213,d_people:generic:headshot:silo:current.png,q_auto:best,f_auto/v1/people/657757/headshot/67/current",
        "ba": 0.471,
        "season_ba": 0.266,
        "difference_ba": 0.205
    },
    {
        "name": "Byron Buxton",
        "player_id": 621439,
        "hits": 7,
        "singles": 4,
        "doubles": 2,
        "triples": 0,
        "home_runs": 1,
        "at_bats": 15,
        "team": "MIN",
        "headshot_url": "https://img.mlbstatic.com/mlb-photos/image/upload/w_213,d_people:generic:headshot:silo:current.png,q_auto:best,f_auto/v1/people/621439/headshot/67/current",
        "ba": 0.467,
        "season_ba": 0.273,
        "difference_ba": 0.194
    },
    {
        "name": "Mike Yastrzemski",
        "player_id": 573262,
        "hits": 7,
        "singles": 5,
        "doubles": 2,
        "triples": 0,
        "home_runs": 0,
        "at_bats": 16,
        "team": "SFG",
        "headshot_url": "https://img.mlbstatic.com/mlb-photos/image/upload/w_213,d_people:generic:headshot:silo:current.png,q_auto:best,f_auto/v1/people/573262/headshot/67/current",
        "ba": 0.438,
        "season_ba": 0.248,
        "difference_ba": 0.19
    },
    {
        "name": "Ernie Clement",
        "player_id": 676391,
        "hits": 10,
        "singles": 7,
        "doubles": 2,
        "triples": 0,
        "home_runs": 1,
        "at_bats": 21,
        "team": "TOR",
        "headshot_url": "https://img.mlbstatic.com/mlb-photos/image/upload/w_213,d_people:generic:headshot:silo:current.png,q_auto:best,f_auto/v1/people/676391/headshot/67/current",
        "ba": 0.476,
        "season_ba": 0.292,
        "difference_ba": 0.184
    },
    {
        "name": "Willi Castro",
        "player_id": 650489,
        "hits": 9,
        "singles": 5,
        "doubles": 2,
        "triples": 1,
        "home_runs": 1,
        "at_bats": 19,
        "team": "MIN",
        "headshot_url": "https://img.mlbstatic.com/mlb-photos/image/upload/w_213,d_people:generic:headshot:silo:current.png,q_auto:best,f_auto/v1/people/650489/headshot/67/current",
        "ba": 0.474,
        "season_ba": 0.29,
        "difference_ba": 0.184
    }
]