[
    {
        "name": "Addison Barger",
        "player_id": 680718,
        "hits": 10,
        "singles": 8,
        "doubles": 2,
        "triples": 0,
        "home_runs": 0,
        "at_bats": 20,
        "team": "TOR",
        "headshot_url": "https://img.mlbstatic.com/mlb-photos/image/upload/w_213,d_people:generic:headshot:silo:current.png,q_auto:best,f_auto/v1/people/680718/headshot/67/current",
        "obp": 0.565,
        "season_obp": 0.301,
        "difference_obp": 0.264
    },
    {
        "name": "Mitch Garver",
        "player_id": 641598,
        "hits": 1,
        "singles": 0,
        "doubles": 0,
        "triples": 1,
        "home_runs": 0,
        "at_bats": 2,
        "team": "SEA",
        "headshot_url": "https://img.mlbstatic.com/mlb-photos/image/upload/w_213,d_people:generic:headshot:silo:current.png,q_auto:best,f_auto/v1/people/641598/headshot/67/current",
        "obp": 0.5,
        "season_obp": 0.297,
        "difference_obp": 0.203
    },
    {
        "name": "Josh Naylor",
        "player_id": 647304,
        "hits": 7,
        "singles": 5,
        "doubles": 0,
        "triples": 0,
        "home_runs": 2,
        "at_bats": 16,
        "team": "- - -",
        "headshot_url": "https://img.mlbstatic.com/mlb-photos/image/upload/w_213,d_people:generic:headshot:silo:current.png,q_auto:best,f_auto/v1/people/647304/headshot/67/current",
        "obp": 0.526,
        "season_obp": 0.353,
        "difference_obp": 0.173
    },
    {
        "name": "Michael Busch",
        "player_id": 683737,
        "hits": 1,
        "singles": 1,
        "doubles": 0,
        "triples": 0,
        "home_runs": 0,
        "at_bats": 3,
        "team": "CHC",
        "headshot_url": "https://img.mlbstatic.com/mlb-photos/image/upload/w_213,d_people:generic:headshot:silo:current.png,q_auto:best,f_auto/v1/people/683737/headshot/67/current",
        "obp": 0.5,
        "season_obp": 0.343,
        "difference_obp": 0.157
    },
    {
        "name": "Nico Hoerner",
        "player_id": 663538,
        "hits": 1,
        "singles": 1,
        "doubles": 0,
        "triples": 0,
        "home_runs": 0,
        "at_bats": 3,
        "team": "CHC",
        "headshot_url": "https://img.mlbstatic.com/mlb-photos/image/upload/w_213,d_people:generic:headshot:silo:current.png,q_auto:best,f_auto/v1/people/663538/headshot/67/current",
        "obp": 0.5,
        "season_obp": 0.345,
        "difference_obp": 0.155
    }
]