[
    {
        "name": "Kerry Carpenter",
        "player_id": 681481,
        "hits": 6,
        "singles": 2,
        "doubles": 0,
        "triples": 1,
        "home_runs": 3,
        "at_bats": 13,
        "team": "DET",
        "headshot_url": "https://img.mlbstatic.com/mlb-photos/image/upload/w_213,d_people:generic:headshot:silo:current.png,q_auto:best,f_auto/v1/people/681481/headshot/67/current",
        "ops": 1.769,
        "season_ops": 0.78,
        "difference_ops": 0.989
    },
    {
        "name": "George Springer",
        "player_id": 543807,
        "hits": 10,
        "singles": 6,
        "doubles": 0,
        "triples": 0,
        "home_runs": 4,
        "at_bats": 18,
        "team": "TOR",
        "headshot_url": "https://img.mlbstatic.com/mlb-photos/image/upload/w_213,d_people:generic:headshot:silo:current.png,q_auto:best,f_auto/v1/people/543807/headshot/67/current",
        "ops": 1.859,
        "season_ops": 0.892,
        "difference_ops": 0.967
    },
    {
        "name": "Randy Arozarena",
        "player_id": 668227,
        "hits": 8,
        "singles": 3,
        "doubles": 0,
        "triples": 0,
        "home_runs": 5,
        "at_bats": 19,
        "team": "SEA",
        "headshot_url": "https://img.mlbstatic.com/mlb-photos/image/upload/w_213,d_people:generic:headshot:silo:current.png,q_auto:best,f_auto/v1/people/668227/headshot/67/current",
        "ops": 1.611,
        "season_ops": 0.802,
        "difference_ops": 0.809
    },
    {
        "name": "Trevor Story",
        "player_id": 596115,
        "hits": 11,
        "singles": 6,
        "doubles": 3,
        "triples": 0,
        "home_runs": 2,
        "at_bats": 21,
        "team": "BOS",
        "headshot_url": "https://img.mlbstatic.com/mlb-photos/image/upload/w_213,d_people:generic:headshot:silo:current.png,q_auto:best,f_auto/v1/people/596115/headshot/67/current",
        "ops": 1.498,
        "season_ops": 0.697,
        "difference_ops": 0.801
    },
    {
        "name": "Michael Busch",
        "player_id": 683737,
        "hits": 8,
        "singles": 5,
        "doubles": 0,
        "triples": 0,
        "home_runs": 3,
        "at_bats": 16,
        "team": "CHC",
        "headshot_url": "https://img.mlbstatic.com/mlb-photos/image/upload/w_213,d_people:generic:headshot:silo:current.png,q_auto:best,f_auto/v1/people/683737/headshot/67/current",
        "ops": 1.592,
        "season_ops": 0.92,
        "difference_ops": 0.672
    }
]